main.py
iflow_mcp_johnnyinlee_lol_client_mcp-0.1.5.dist-info/licenses/LICENSE
iflow_mcp_johnnyinlee_lol_client_mcp-0.1.5.dist-info/METADATA
iflow_mcp_johnnyinlee_lol_client_mcp-0.1.5.dist-info/WHEEL
iflow_mcp_johnnyinlee_lol_client_mcp-0.1.5.dist-info/entry_points.txt
iflow_mcp_johnnyinlee_lol_client_mcp-0.1.5.dist-info/top_level.txt
iflow_mcp_johnnyinlee_lol_client_mcp-0.1.5.dist-info/RECORD
