Metadata-Version: 2.4
Name: iflow-mcp_johnnyinlee_lol-client-mcp
Version: 0.1.5
Summary: Add your description here
Requires-Python: >=3.11
License-File: LICENSE
Requires-Dist: httpx>=0.28.1
Requires-Dist: mcp[cli]>=1.6.0
Dynamic: license-file
